[
  {
    "name": "theme_info",
    "theme_name": "Hydrogen theme",
    "theme_version": "0.0.0",
    "theme_author": "THEME_AUTHOR",
    "theme_documentation_url": "https:\/\/THEME_DOCUMENTATION_URL.com\/",
    "theme_support_url": "https:\/\/THEME_SUPPORT_URL.com\/"
  },
  {
    "name": "Colors",
    "settings": [
      {
        "type": "color",
        "id": "colors_primary",
        "default": "#FAFAFA",
        "label": "Primary",
        "info": "Text, buttons, etc."
      },
      {
        "type": "color",
        "id": "colors_contrast",
        "default": "#202124",
        "label": "Accent",
        "info": "Backgrounds, borders, etc."
      },
      {
        "type": "color",
        "id": "colors_accent",
        "default": "#EB5628",
        "label": "Labels like \"On sale\""
      }
    ]
  },
  {
    "name": "Typography",
    "settings": [
      {
        "type": "header",
        "content": "Headings"
      },
      {
        "type": "font_picker",
        "id": "type_header_font",
        "default": "helvetica_n4",
        "label": "Font",
        "info": "Selecting a different font can affect the speed of your store. [Learn more about system fonts.](https://help.shopify.com/manual/online-store/os/store-speed/improving-speed#fonts)"
      },
      {
        "type": "header",
        "content": "Body"
      },
      {
        "type": "font_picker",
        "id": "type_body_font",
        "default": "helvetica_n4",
        "label": "Font",
        "info": "Selecting a different font can affect the speed of your store. [Learn more about system fonts.](https://help.shopify.com/manual/online-store/os/store-speed/improving-speed#fonts)"
      }
    ]
  },
  {
    "name": "Favicon",
    "settings": [
      {
        "type": "image_picker",
        "id": "favicon",
        "label": "Favicon image",
        "info": "Will be scaled down to 32 x 32px"
      }
    ]
  }
]
