[
  {
    "name": "theme_info",
    "theme_name": "Hydrogen theme",
    "theme_version": "0.0.0",
    "theme_author": "THEME_AUTHOR",
    "theme_documentation_url": "https://THEME_DOCUMENTATION_URL.com/",
    "theme_support_url": "https://THEME_SUPPORT_URL.com/"
  },
  {
    "name": "Colors",
    "settings": [
      {
        "type": "color",
        "id": "colors_primary",
        "default": "#FAFAFA",
        "label": "Primary",
        "info": "Text, buttons, etc."
      },
      {
        "type": "color",
        "id": "colors_contrast",
        "default": "#202124",
        "label": "Accent",
        "info": "Backgrounds, borders, etc."
      },
      {
        "type": "color",
        "id": "colors_accent",
        "default": "#EB5628",
        "label": "Labels like \"On sale\""
      }
    ]
  },
  {
    "name": "Typography",
    "settings": [
      {
        "type": "header",
        "content": "Headings"
      },
      {
        "type": "font_picker",
        "id": "type_header_font",
        "default": "helvetica_n7",
        "label": "Font",
        "info": "Selecting a different font can affect the speed of your store. [Learn more about system fonts.](https://help.shopify.com/manual/online-store/os/store-speed/improving-speed#fonts)"
      },
      {
        "type": "header",
        "content": "Body"
      },
      {
        "type": "font_picker",
        "id": "type_body_font",
        "default": "helvetica_n4",
        "label": "Font",
        "info": "Selecting a different font can affect the speed of your store. [Learn more about system fonts.](https://help.shopify.com/manual/online-store/os/store-speed/improving-speed#fonts)"
      }
    ]
  },
  {
    "name": "Cart",
    "settings": [
      {
        "type": "select",
        "id": "cart_type",
        "options": [
          {
            "value": "drawer",
            "label": "Drawer"
          },
          {
            "value": "page",
            "label": "Page"
          }
        ],
        "default": "drawer",
        "label": "Cart type"
      },
      {
        "type": "checkbox",
        "id": "show_cart_note",
        "label": "Enable cart note",
        "default": false
      }
    ]
  },
  {
    "name": "Favicon",
    "settings": [
      {
        "type": "image_picker",
        "id": "favicon",
        "label": "Favicon image",
        "info": "Will be scaled down to 32 x 32px"
      }
    ]
  },
  {
    "name": "Social media",
    "settings": [
      {
        "type": "header",
        "content": "Social accounts"
      },
      {
        "type": "text",
        "id": "social_twitter_link",
        "label": "Twitter",
        "info": "https://twitter.com/shopify"
      },
      {
        "type": "text",
        "id": "social_facebook_link",
        "label": "Facebook",
        "info": "https://facebook.com/shopify"
      },
      {
        "type": "text",
        "id": "social_pinterest_link",
        "label": "Pinterest",
        "info": "https://pinterest.com/shopify"
      },
      {
        "type": "text",
        "id": "social_instagram_link",
        "label": "Instagram",
        "info": "http://instagram.com/shopify"
      },
      {
        "type": "text",
        "id": "social_tiktok_link",
        "label": "TikTok",
        "info": "https://tiktok.com/@shopify"
      },
      {
        "type": "text",
        "id": "social_tumblr_link",
        "label": "Tumblr",
        "info": "https://shopify.tumblr.com"
      },
      {
        "type": "text",
        "id": "social_snapchat_link",
        "label": "Snapchat",
        "info": "https://www.snapchat.com/add/shopify"
      },
      {
        "type": "text",
        "id": "social_youtube_link",
        "label": "YouTube",
        "info": "https://www.youtube.com/shopify"
      },
      {
        "type": "text",
        "id": "social_vimeo_link",
        "label": "Vimeo",
        "info": "https://vimeo.com/shopify"
      }
    ]
  }
]
